{
  "_class": "symbolInstance",
  "do_objectID": "C5D8455B-CAF7-4BAB-864D-FD16B1174327",
  "exportOptions": {
    "_class": "exportOptions",
    "do_objectID": "DDD44C49-5272-4C90-8DFA-E6039C4B6395",
    "exportFormats": [
    ],
    "includedLayerIds": [
    ],
    "layerOptions": 0,
    "shouldTrim": false
  },
  "frame": {
    "_class": "rect",
    "constrainProportions": false,
    "do_objectID": "FC2B777E-5AFC-4D03-936A-2BA629AAFBA3",
    "height": 1,
    "width": 1206,
    "x": 0,
    "y": 47
  },
  "horizontalSpacing": 0,
  "isFlippedHorizontal": false,
  "isFlippedVertical": false,
  "isLocked": false,
  "isVisible": true,
  "layerListExpandedType": 0,
  "name": "statics/tabs/sub/bottom-bar",
  "nameIsFixed": false,
  "overrideValues": [
  ],
  "overrides": {
  },
  "resizingConstraint": 63,
  "resizingType": 0,
  "rotation": 0,
  "scale": 1,
  "shouldBreakMaskChain": false,
  "style": {
    "_class": "style",
    "do_objectID": "1437BB59-4192-4007-A6AF-0D30B10FE841",
    "endDecorationType": 0,
    "miterLimit": 10,
    "startDecorationType": 0
  },
  "symbolID": "01CAB83F-001D-47D1-8736-504AD00BD889",
  "verticalSpacing": 0
}