{
  "_class": "group",
  "do_objectID": "AAD51BC3-CD38-4AD8-80B6-A2208AC63DF6",
  "exportOptions": {
    "_class": "exportOptions",
    "exportFormats": [
    ],
    "includedLayerIds": [
    ],
    "layerOptions": 0,
    "shouldTrim": false
  },
  "frame": {
    "_class": "rect",
    "constrainProportions": false,
    "height": 67,
    "width": 888,
    "x": 0,
    "y": 75
  },
  "hasClickThrough": false,
  "isFlippedHorizontal": false,
  "isFlippedVertical": false,
  "isLocked": false,
  "isVisible": true,
  "layerListExpandedType": 0,
  "layers": [
    {
      "class": "shapeGroup",
      "id": "652996C5-DD3F-4F32-A654-1C2F0C1AF23F"
    },
    {
      "class": "text",
      "id": "7430CC2E-1B22-4228-8773-0658AA6EA292"
    }
  ],
  "name": "Blue row",
  "nameIsFixed": true,
  "resizingConstraint": 63,
  "resizingType": 0,
  "rotation": 0,
  "shouldBreakMaskChain": false,
  "style": {
    "_class": "style",
    "endDecorationType": 0,
    "miterLimit": 10,
    "startDecorationType": 0
  }
}