{
  "_class": "group",
  "do_objectID": "DE9432F6-99FC-4EAE-AB7E-DCEDA8AB7352",
  "exportOptions": {
    "_class": "exportOptions",
    "do_objectID": "064FFA64-819F-4115-AA36-7E55F0AC711A",
    "exportFormats": [
    ],
    "includedLayerIds": [
    ],
    "layerOptions": 0,
    "shouldTrim": false
  },
  "frame": {
    "_class": "rect",
    "constrainProportions": false,
    "do_objectID": "C3F16521-A1C1-4686-B06F-E9D3144627BA",
    "height": 49,
    "width": 555,
    "x": 0,
    "y": 61
  },
  "hasClickThrough": false,
  "isFlippedHorizontal": false,
  "isFlippedVertical": false,
  "isLocked": false,
  "isVisible": true,
  "layerListExpandedType": 0,
  "layers": [
    {
      "class": "shapeGroup",
      "id": "79EA1007-8C35-4BB9-ADD3-8A9784BF27AC"
    },
    {
      "class": "shapeGroup",
      "id": "203973F4-7D25-4658-BC5E-908BFEA06CF9"
    },
    {
      "class": "text",
      "id": "600F5595-6B81-4C1E-9739-777BA48CCCA8"
    },
    {
      "class": "text",
      "id": "76A311AC-1F0F-4382-853F-63F948C476E9"
    }
  ],
  "name": "First Name Copy",
  "nameIsFixed": true,
  "resizingConstraint": 63,
  "resizingType": 0,
  "rotation": 0,
  "shouldBreakMaskChain": false,
  "style": {
    "_class": "style",
    "do_objectID": "F16CC4F3-8E55-4AF0-9A47-6296DAEF4FD1",
    "endDecorationType": 0,
    "miterLimit": 10,
    "startDecorationType": 0
  }
}