{
  "_class": "symbolInstance",
  "do_objectID": "0840AB32-FDC5-4901-A7BC-ED7F2A068F61",
  "exportOptions": {
    "_class": "exportOptions",
    "do_objectID": "F25ED4B4-160F-4A6E-AA21-C651B1F33975",
    "exportFormats": [
    ],
    "includedLayerIds": [
    ],
    "layerOptions": 0,
    "shouldTrim": false
  },
  "frame": {
    "_class": "rect",
    "constrainProportions": false,
    "do_objectID": "63931B37-21FB-42B2-8559-F69E7A1C4DFF",
    "height": 22,
    "width": 21,
    "x": 325,
    "y": 17
  },
  "horizontalSpacing": 0,
  "isFlippedHorizontal": false,
  "isFlippedVertical": false,
  "isLocked": false,
  "isVisible": true,
  "layerListExpandedType": 0,
  "name": "icons/calendar",
  "nameIsFixed": false,
  "overrideValues": [
  ],
  "overrides": {
  },
  "resizingConstraint": 63,
  "resizingType": 0,
  "rotation": 0,
  "scale": 1,
  "shouldBreakMaskChain": false,
  "style": {
    "_class": "style",
    "do_objectID": "9B1A51F5-6A87-4C58-8314-5A13BABF22AE",
    "endDecorationType": 0,
    "miterLimit": 10,
    "startDecorationType": 0
  },
  "symbolID": "CD236BC2-12F4-41B3-BA7B-2636EB5203F6",
  "verticalSpacing": 0
}