{
  "_class": "symbolInstance",
  "do_objectID": "FAC81165-7B56-4EEE-A2F3-B09CB512D285",
  "exportOptions": {
    "_class": "exportOptions",
    "do_objectID": "8987BB52-BE1F-4ECD-820E-70D43F258E6B",
    "exportFormats": [
    ],
    "includedLayerIds": [
    ],
    "layerOptions": 0,
    "shouldTrim": false
  },
  "frame": {
    "_class": "rect",
    "constrainProportions": false,
    "do_objectID": "299A6F9F-0140-454A-86EA-9D2D967FD5F6",
    "height": 40,
    "width": 263,
    "x": 0,
    "y": 0
  },
  "horizontalSpacing": 0,
  "isFlippedHorizontal": false,
  "isFlippedVertical": false,
  "isLocked": false,
  "isVisible": true,
  "layerListExpandedType": 0,
  "name": "buttons/btn-needs-analysis",
  "nameIsFixed": false,
  "overrideValues": [
  ],
  "overrides": {
  },
  "resizingConstraint": 63,
  "resizingType": 0,
  "rotation": 0,
  "scale": 1,
  "shouldBreakMaskChain": false,
  "style": {
    "_class": "style",
    "do_objectID": "63B4B1A9-4F32-4A4A-9A4D-42C0F0582D2B",
    "endDecorationType": 0,
    "miterLimit": 10,
    "startDecorationType": 0
  },
  "symbolID": "0DB1D518-1B65-4256-A5AB-8EA18C5C806B",
  "verticalSpacing": 0
}