{
  "_class": "group",
  "do_objectID": "07F577E6-A2AB-450D-A372-FA1415CC567B",
  "exportOptions": {
    "_class": "exportOptions",
    "exportFormats": [
    ],
    "includedLayerIds": [
    ],
    "layerOptions": 0,
    "shouldTrim": false
  },
  "frame": {
    "_class": "rect",
    "constrainProportions": false,
    "height": 30,
    "width": 30,
    "x": 0,
    "y": 75
  },
  "hasClickThrough": false,
  "isFlippedHorizontal": false,
  "isFlippedVertical": false,
  "isLocked": false,
  "isVisible": true,
  "layerListExpandedType": 0,
  "layers": [
    {
      "class": "shapeGroup",
      "id": "614D202C-A787-49B7-8957-258729EAAD38"
    },
    {
      "class": "text",
      "id": "D6852554-0754-4006-B2BD-595BFFC6E912"
    }
  ],
  "name": "4",
  "nameIsFixed": true,
  "resizingConstraint": 63,
  "resizingType": 0,
  "rotation": 0,
  "shouldBreakMaskChain": false,
  "style": {
    "_class": "style",
    "endDecorationType": 0,
    "miterLimit": 10,
    "startDecorationType": 0
  }
}