{
  "_class": "group",
  "do_objectID": "0A08D418-7033-4B89-8E1F-ED02C2EEFECF",
  "exportOptions": {
    "_class": "exportOptions",
    "exportFormats": [
    ],
    "includedLayerIds": [
    ],
    "layerOptions": 0,
    "shouldTrim": false
  },
  "frame": {
    "_class": "rect",
    "constrainProportions": false,
    "height": 50,
    "width": 272,
    "x": 22,
    "y": 208
  },
  "hasClickThrough": false,
  "isFlippedHorizontal": false,
  "isFlippedVertical": false,
  "isLocked": false,
  "isVisible": true,
  "layerListExpandedType": 0,
  "layers": [
    {
      "class": "shapeGroup",
      "id": "96960B84-C1CB-4F3E-90B0-F130592285D4"
    },
    {
      "class": "text",
      "id": "ACD77334-8883-477D-AF5B-148A6E3625AD"
    },
    {
      "class": "symbolInstance",
      "id": "8CBD50DB-A078-40BD-AE10-682C12442835"
    }
  ],
  "name": "Group 6",
  "nameIsFixed": false,
  "resizingConstraint": 63,
  "resizingType": 0,
  "rotation": 0,
  "shouldBreakMaskChain": false,
  "style": {
    "_class": "style",
    "endDecorationType": 0,
    "miterLimit": 10,
    "startDecorationType": 0
  }
}