{
  "_class": "group",
  "do_objectID": "8503C12C-F4F8-4D60-BB0C-E1A1E82F6A9B",
  "exportOptions": {
    "_class": "exportOptions",
    "exportFormats": [
    ],
    "includedLayerIds": [
    ],
    "layerOptions": 0,
    "shouldTrim": false
  },
  "frame": {
    "_class": "rect",
    "constrainProportions": false,
    "height": 58,
    "width": 500,
    "x": 11,
    "y": 336
  },
  "hasClickThrough": false,
  "isFlippedHorizontal": false,
  "isFlippedVertical": false,
  "isLocked": false,
  "isVisible": true,
  "layerListExpandedType": 0,
  "layers": [
    {
      "class": "shapeGroup",
      "id": "37BC36EC-CF8A-4477-86A9-485653EF67F8"
    },
    {
      "class": "text",
      "id": "F44C84E2-4247-461B-8C43-00B6A88E920A"
    },
    {
      "class": "text",
      "id": "010636B6-F2FD-4747-9B7D-B442ED3FDEE5"
    },
    {
      "class": "text",
      "id": "9205C82A-0D59-4702-AE36-1E8ABD187352"
    }
  ],
  "name": "Group 3 Copy 3",
  "nameIsFixed": false,
  "resizingConstraint": 63,
  "resizingType": 0,
  "rotation": 0,
  "shouldBreakMaskChain": false,
  "style": {
    "_class": "style",
    "endDecorationType": 0,
    "miterLimit": 10,
    "startDecorationType": 0
  }
}