{
  "_class": "group",
  "do_objectID": "6DC33507-E393-4CAD-AD3C-870198BF58A3",
  "exportOptions": {
    "_class": "exportOptions",
    "do_objectID": "A259E729-AA8B-4288-BEC1-D5A2B5D2FCC5",
    "exportFormats": [
    ],
    "includedLayerIds": [
    ],
    "layerOptions": 0,
    "shouldTrim": false
  },
  "frame": {
    "_class": "rect",
    "constrainProportions": false,
    "do_objectID": "2C729FE2-E19A-43EC-BD04-D91B38ADD887",
    "height": 49,
    "width": 344,
    "x": 23,
    "y": 614
  },
  "hasClickThrough": false,
  "isFlippedHorizontal": false,
  "isFlippedVertical": false,
  "isLocked": false,
  "isVisible": true,
  "layerListExpandedType": 0,
  "layers": [
    {
      "class": "shapeGroup",
      "id": "A4574C1F-61CE-4BD6-AAEC-5C6DCF9DC78F"
    },
    {
      "class": "shapeGroup",
      "id": "A348AAA8-B2BC-4508-B0F6-5CA2339F9B29"
    },
    {
      "class": "text",
      "id": "83A96175-E753-442B-AA19-7DCE5EC0F68D"
    },
    {
      "class": "text",
      "id": "2DACE2B6-B0ED-4D88-8212-8F606267289A"
    }
  ],
  "name": "Street Address 02 Copy",
  "nameIsFixed": true,
  "resizingConstraint": 63,
  "resizingType": 0,
  "rotation": 0,
  "shouldBreakMaskChain": false,
  "style": {
    "_class": "style",
    "do_objectID": "519035E3-F367-4327-874D-253E5000B905",
    "endDecorationType": 0,
    "miterLimit": 10,
    "startDecorationType": 0
  }
}