{
  "_class": "group",
  "do_objectID": "6E769C93-BE9F-4DDF-8BD1-53A0C29F205C",
  "exportOptions": {
    "_class": "exportOptions",
    "do_objectID": "1821E2AD-5E33-483A-A72B-7626094C8589",
    "exportFormats": [
    ],
    "includedLayerIds": [
    ],
    "layerOptions": 0,
    "shouldTrim": false
  },
  "frame": {
    "_class": "rect",
    "constrainProportions": false,
    "do_objectID": "6DA1D9FD-B115-4B3A-90D8-75C37EF16529",
    "height": 49,
    "width": 345,
    "x": 0,
    "y": 32
  },
  "hasClickThrough": false,
  "isFlippedHorizontal": false,
  "isFlippedVertical": false,
  "isLocked": false,
  "isVisible": true,
  "layerListExpandedType": 0,
  "layers": [
    {
      "class": "shapeGroup",
      "id": "D4A22E62-FF5F-4360-AA6C-5E652F4551D5"
    },
    {
      "class": "shapeGroup",
      "id": "FD972739-D9B5-4121-B35A-4528EC459EBB"
    },
    {
      "class": "text",
      "id": "2C0D2773-5DEC-46E8-B19F-2A8A4C24EC05"
    },
    {
      "class": "text",
      "id": "F214B79C-7485-4347-9CBD-A2E0247A516F"
    },
    {
      "class": "text",
      "id": "42C5DBBA-4B5E-43D8-AF4D-0662D8CB68ED"
    }
  ],
  "name": "Gender",
  "nameIsFixed": true,
  "resizingConstraint": 63,
  "resizingType": 0,
  "rotation": 0,
  "shouldBreakMaskChain": false,
  "style": {
    "_class": "style",
    "do_objectID": "A8476F3E-29D4-4CB8-9567-5E70366289FF",
    "endDecorationType": 0,
    "miterLimit": 10,
    "startDecorationType": 0
  }
}