{
  "_class": "group",
  "do_objectID": "9E6D1669-D25B-46A4-9985-279FF58B979D",
  "exportOptions": {
    "_class": "exportOptions",
    "exportFormats": [
    ],
    "includedLayerIds": [
    ],
    "layerOptions": 0,
    "shouldTrim": false
  },
  "frame": {
    "_class": "rect",
    "constrainProportions": false,
    "height": 53,
    "width": 53,
    "x": 29,
    "y": 680
  },
  "hasClickThrough": false,
  "isFlippedHorizontal": false,
  "isFlippedVertical": false,
  "isLocked": false,
  "isVisible": true,
  "layerListExpandedType": 0,
  "layers": [
    {
      "class": "shapeGroup",
      "id": "F24B2440-7806-4082-8384-98A230829113"
    },
    {
      "class": "shapeGroup",
      "id": "81286B34-2DD1-476C-BC40-18B10FCDA805"
    }
  ],
  "name": "Button",
  "nameIsFixed": true,
  "resizingConstraint": 63,
  "resizingType": 0,
  "rotation": 0,
  "shouldBreakMaskChain": false,
  "style": {
    "_class": "style",
    "endDecorationType": 0,
    "miterLimit": 10,
    "startDecorationType": 0
  }
}