{
  "_class": "group",
  "do_objectID": "4EEA1FD3-ADD5-446D-A3CF-6BE00EEEBC13",
  "exportOptions": {
    "_class": "exportOptions",
    "exportFormats": [
    ],
    "includedLayerIds": [
    ],
    "layerOptions": 0,
    "shouldTrim": false
  },
  "frame": {
    "_class": "rect",
    "constrainProportions": false,
    "height": 59,
    "width": 987,
    "x": 47,
    "y": 0
  },
  "hasClickThrough": false,
  "isFlippedHorizontal": false,
  "isFlippedVertical": false,
  "isLocked": false,
  "isVisible": true,
  "layerListExpandedType": 0,
  "layers": [
    {
      "class": "shapeGroup",
      "id": "60E5F9FB-390E-4223-9B60-98762B96CA15"
    },
    {
      "class": "shapeGroup",
      "id": "2AE96B1A-167E-48FD-9AE1-416606DF41F0"
    },
    {
      "class": "text",
      "id": "C5855764-FA73-4EA9-9EF6-EF90EC61D63F"
    },
    {
      "class": "text",
      "id": "AF9B696E-68B4-4FBE-83DC-E8958C865D70"
    },
    {
      "class": "text",
      "id": "28B5DD21-6596-4E4F-AE8A-AF981C460B27"
    },
    {
      "class": "text",
      "id": "3DDE1441-2D96-43E4-9790-634F92D84BDC"
    }
  ],
  "name": "row",
  "nameIsFixed": true,
  "resizingConstraint": 63,
  "resizingType": 0,
  "rotation": 0,
  "shouldBreakMaskChain": false,
  "style": {
    "_class": "style",
    "endDecorationType": 0,
    "miterLimit": 10,
    "startDecorationType": 0
  }
}