{
  "_class": "group",
  "do_objectID": "1A23C3EF-F0E6-4A4A-A27D-9DD7E2D1D6DA",
  "exportOptions": {
    "_class": "exportOptions",
    "do_objectID": "D093601C-8461-4369-9BEC-4277F963308A",
    "exportFormats": [
    ],
    "includedLayerIds": [
    ],
    "layerOptions": 0,
    "shouldTrim": false
  },
  "frame": {
    "_class": "rect",
    "constrainProportions": false,
    "do_objectID": "9C6547BB-A1D2-4217-BA5F-623EDA257EC9",
    "height": 985,
    "width": 1205,
    "x": 0,
    "y": 0
  },
  "hasClickThrough": false,
  "isFlippedHorizontal": false,
  "isFlippedVertical": false,
  "isLocked": false,
  "isVisible": true,
  "layerListExpandedType": 2,
  "layers": [
    {
      "class": "shapeGroup",
      "id": "DF00D523-C62A-4CA2-8616-286D75875B71"
    },
    {
      "class": "group",
      "id": "743973A6-11FB-4CE8-A181-FF5B0B745E3C"
    }
  ],
  "name": "Drawer",
  "nameIsFixed": true,
  "resizingConstraint": 63,
  "resizingType": 0,
  "rotation": 0,
  "shouldBreakMaskChain": false,
  "style": {
    "_class": "style",
    "do_objectID": "DFBE9624-D1B5-40A6-B421-EF8A9E8FEE35",
    "endDecorationType": 0,
    "miterLimit": 10,
    "startDecorationType": 0
  }
}