{
  "_class": "group",
  "do_objectID": "3FCC95C9-43FE-440B-B89D-DA2595C06EF7",
  "exportOptions": {
    "_class": "exportOptions",
    "do_objectID": "7A075F25-034A-4E0D-81B6-4640A9CE3E6F",
    "exportFormats": [
    ],
    "includedLayerIds": [
    ],
    "layerOptions": 0,
    "shouldTrim": false
  },
  "frame": {
    "_class": "rect",
    "constrainProportions": false,
    "do_objectID": "B1ECFDF7-0C6B-401C-81AA-620844312B3F",
    "height": 49,
    "width": 345,
    "x": 375,
    "y": 128
  },
  "hasClickThrough": false,
  "isFlippedHorizontal": false,
  "isFlippedVertical": false,
  "isLocked": false,
  "isVisible": true,
  "layerListExpandedType": 0,
  "layers": [
    {
      "class": "shapeGroup",
      "id": "D1763B34-01E3-4772-AF54-4517B58F70B1"
    },
    {
      "class": "shapeGroup",
      "id": "77CEA752-4C61-4C0A-8275-B7E6ED3BF7F1"
    },
    {
      "class": "text",
      "id": "30E2DC79-B2A0-4FE9-9C73-A2E3FE63F068"
    },
    {
      "class": "text",
      "id": "2AB77578-41B2-4D53-8C2A-5C2E051EA046"
    },
    {
      "class": "text",
      "id": "D1746329-50A3-407B-BA20-6E3A88A2E3D7"
    }
  ],
  "name": "Gender Copy 4",
  "nameIsFixed": true,
  "resizingConstraint": 63,
  "resizingType": 0,
  "rotation": 0,
  "shouldBreakMaskChain": false,
  "style": {
    "_class": "style",
    "do_objectID": "FF9C0A82-47B6-455E-BFF2-2FFD7E9387F5",
    "endDecorationType": 0,
    "miterLimit": 10,
    "startDecorationType": 0
  }
}