{
  "_class": "shapeGroup",
  "clippingMaskMode": 0,
  "do_objectID": "966FF4A2-2727-4F68-8E37-260D36D26850",
  "exportOptions": {
    "_class": "exportOptions",
    "do_objectID": "3037B474-B192-48DE-A391-737350C3B1A4",
    "exportFormats": [
    ],
    "includedLayerIds": [
    ],
    "layerOptions": 0,
    "shouldTrim": false
  },
  "frame": {
    "_class": "rect",
    "constrainProportions": true,
    "do_objectID": "57DCF5CB-DBDC-4D10-AB39-12F2FD3DC774",
    "height": 10,
    "width": 10,
    "x": 40,
    "y": 2
  },
  "hasClickThrough": false,
  "hasClippingMask": false,
  "isFlippedHorizontal": false,
  "isFlippedVertical": false,
  "isLocked": false,
  "isVisible": true,
  "layerListExpandedType": 0,
  "layers": [
    {
      "class": "shapePath",
      "id": "B5D32D38-6BF1-48DA-AE4D-5F72873B81AA"
    }
  ],
  "name": "Fill 9",
  "nameIsFixed": false,
  "resizingConstraint": 63,
  "resizingType": 0,
  "rotation": 0,
  "shouldBreakMaskChain": false,
  "style": {
    "_class": "style",
    "do_objectID": "071095D8-1652-4FDE-AF1E-B588C90E03C1",
    "endDecorationType": 0,
    "fills": [
      {
        "_class": "fill",
        "color": {
          "_class": "color",
          "alpha": 1,
          "blue": 0.6,
          "green": 0.6,
          "red": 0.6
        },
        "fillType": 0,
        "isEnabled": true,
        "noiseIndex": 0,
        "noiseIntensity": 0,
        "patternFillType": 1,
        "patternTileScale": 1
      }
    ],
    "miterLimit": 10,
    "startDecorationType": 0
  },
  "windingRule": 1
}